iguala/__init__.py
iguala/helpers.py
iguala/matchers.py
iguala/paths.py
iguala-0.5.2.dist-info/LICENSE
iguala-0.5.2.dist-info/METADATA
iguala-0.5.2.dist-info/WHEEL
iguala-0.5.2.dist-info/top_level.txt
iguala-0.5.2.dist-info/RECORD
