Metadata-Version: 2.1
Name: iguala
Version: 0.5.2
Summary: Non-linear pattern matching for Python's objects, or rexep-like for objects
Home-page: https://github.com/aranega/iguala
Author: Vincent Aranega
Author-email: vincent.aranega@gmail.com
License: BSD 3-Clause
Keywords: pattern matching matcher regexp graph query term rewriting
Classifier: Development Status :: 4 - Beta
Classifier: Programming Language :: Python
Classifier: Programming Language :: Python :: 3.7
Classifier: Programming Language :: Python :: 3.8
Classifier: Programming Language :: Python :: 3.9
Classifier: Programming Language :: Python :: 3.10
Classifier: Operating System :: OS Independent
Classifier: Intended Audience :: Developers
Classifier: Topic :: Software Development
Classifier: Topic :: Software Development :: Libraries
Classifier: License :: OSI Approved :: BSD License
License-File: LICENSE
